cachefunk/__init__.py
cachefunk/cli.py
cachefunk/funk.py
cachefunk/utils.py
cachefunk-0.1.0.dist-info/DESCRIPTION.rst
cachefunk-0.1.0.dist-info/METADATA
cachefunk-0.1.0.dist-info/RECORD
cachefunk-0.1.0.dist-info/WHEEL
cachefunk-0.1.0.dist-info/entry_points.txt
cachefunk-0.1.0.dist-info/metadata.json
cachefunk-0.1.0.dist-info/top_level.txt
