Metadata-Version: 2.0
Name: cachefunk
Version: 0.1.0
Summary: Sitemap.xml cache warmer
Home-page: https://github.com/ashwoods/cachefunk
Author: Ashley Camba Garrido
Author-email: ashwoods@gmail.com
License: MIT
Platform: UNKNOWN
Classifier: Development Status :: 3 - Alpha
Classifier: Intended Audience :: Developers
Classifier: License :: OSI Approved :: MIT License
Classifier: Operating System :: OS Independent
Classifier: Programming Language :: Python
Classifier: Programming Language :: Python :: 3.5
Classifier: Programming Language :: Python :: 3.6
Classifier: Topic :: Utilities
Requires-Dist: attrs
Requires-Dist: cached-property
Requires-Dist: click
Requires-Dist: click-log
Requires-Dist: grequests
Requires-Dist: requests
Requires-Dist: structlog
Requires-Dist: tqdm
